LICENSE
README.md
setup.py
nembem/__init__.py
nembem/dtu_10_mw_class.py
nembem/test_turbulence.py
nembem.egg-info/PKG-INFO
nembem.egg-info/SOURCES.txt
nembem.egg-info/dependency_links.txt
nembem.egg-info/top_level.txt