Metadata-Version: 2.1
Name: nembem
Version: 0.2
Summary: nembem_package
Author: Adam and Toke
License-File: LICENSE
